Workbook

Sheet Datos
A1: Frutas | B1: Inversión (MIL) | C1: Precio en K | D1: Precio de ganacia en K | E1: Cantidad | F1: Nombre del comprador | G1: Total | H1: Ronda
A2: Pera | B2: 2 | C2: 2.5 | E2: 1 | F2: Juan Esteban | G2: 2.5 | H2: 2
A3: Piña | B3: 4 | C3: 6 | D3: 8 | E3: 1 | F3: David | G3: 8 | H3: 3
A4: Papaya | B4: 4 | C4: 6 | E4: 3 | F4: Antwone | G4: 18 | H4: 1
A5: Manzana | B5: 2 | C5: 3.5 | E5: 1 | F5: Sara | G5: 3.5 | H5: 1
A6: Banano | B6: 1 | C6: 4 | E6: 1 | F6: Antwone | G6: 4 | H6: 1
A7: Uva | B7: 6 | C7: 9 | D7: 10 | E7: 1 | F7: Lina | G7: 10 | H7: 3
A8: Lima | B8: 1 | C8: 2 | E8: 2 | F8: Mariana | G8: 4 | H8: 2
A9: Pitahaya | B9: 5 | C9: 8 | E9: 1 | F9: Antwone | G9: 8 | H9: 1
A10: Cereza | B10: 4 | C10: 6 | E10: 1 | F10: Alisson | G10: 6 | H10: 3
A11: Arándanos | B11: 5 | C11: 8 | D11: 10 | E11: 1 | F11: David | G11: 10 | H11: 3
A12: Total | B12: =SUM(B2:B11) -> 34 | C12: =SUM(C2:C11) -> 55 | D12: =SUM(D2:D11) -> 28 | E12: =SUM(E2:E11) -> 13 | F12: =SUM(F2:F11) -> 0 | G12: =SUM(G2:G11) -> 74
B16: Gasto (compra) | C16: Venta por ronda | F16: Productos | G16: Precio de venta | H16: Ganancias
A17: Ronda 1 | B17: 9.5 | C17: =G9+G6+G5+G4 -> 33.5 | E17: Media | F17: =AVERAGE(B2:B11) -> 3.4 | G17: =AVERAGE(C2:C11) -> 5.5 | H17: =AVERAGE(G2:G11) -> 7.4
A18: Ronda 2 | B18: 7.5 | C18: =G2+G8 -> 6.5 | E18: Moda | F18: =MODE(B2:B11) -> 4 | G18: =MODE(C2:C11) -> 6 | H18: =MODE(G2:G11) -> 8
A19: Ronda 3 | B19: 4 | C19: =G11+G10+G7+G3 -> 34 | E19: Varianza muestral | F19: =VAR(B2:B11) -> 3.1555556 | G19: =VAR(C2:C11) -> 5.8888889 | H19: =VAR(G2:G11) -> 21.211111
A20: Total gasto | B20: =SUM(B17:B19) -> 21 | C20: =SUM(C17:C19) -> 74 | E20: Varianza pob | F20: =VARP(B2:B11) -> 2.84 | G20: =VARP(C2:C11) -> 5.3 | H20: =VARP(G2:G11) -> 19.09
A22: Ganancias | B22: =G12-B12-B20 -> 19

Sheet Limpieza
A1: id_venta | B1: vendedor | C1: comprador | D1: producto | E1: categoria | F1: precio_lista_limpio | G1: precio_venta_limpio | H1: cantidad | I1: calificacion | J1: ronda | K1: clave | L1: duplicado | M1: valor_faltante | N1: incluir_analisis | O1: precio_venta_final | P1: cantidad_final | Q1: calificacion_final
A2: ='[1]Hoja 1'!A2 -> 1 | B2: ='[1]Hoja 1'!B2 -> GRUPO frutas | C2: ='[1]Hoja 1'!C2 -> GRUPO MAQUILLAJE | D2: ='[1]Hoja 1'!D2 -> Pera | E2: ='[1]Hoja 1'!E2 -> Frutas mediana | F2: =IFERROR(VALUE(SUBSTITUTE('[1]Hoja 1'!F2,".","")),"") -> 2.5 | G2: =IFERROR(VALUE(SUBSTITUTE('[1]Hoja 1'!G2,".","")),"") -> 2.5 | H2: ='[1]Hoja 1'!H2 -> 1 | I2: ='[1]Hoja 1'!I2 -> 5 | J2: ='[1]Hoja 1'!J2 -> 2 | K2: =B2&"|"&D2&"|"&J2 -> GRUPO frutas|Pera|2 | L2: =COUNTIFS($K$2:K2,K2)>1 -> FALSE | M2: =(G2="") -> FALSE | N2: =NOT(OR(L2,M2)) -> TRUE | O2: =IF(N2,G2,"") -> 2.5 | P2: =IF(N2,H2,"") -> 1 | Q2: =IF(N2,I2,"") -> 5
A3: ='[1]Hoja 1'!A3 -> 2 | B3: ='[1]Hoja 1'!B3 -> GRUPO frutas | C3: ='[1]Hoja 1'!C3 -> GRUPO SUPER | D3: ='[1]Hoja 1'!D3 -> Piña | E3: ='[1]Hoja 1'!E3 -> Frutas grande | F3: =IFERROR(VALUE(SUBSTITUTE('[1]Hoja 1'!F3,".","")),"") -> 6 | G3: =IFERROR(VALUE(SUBSTITUTE(SUBSTITUTE('[1]Hoja 1'!G3,".",""),",",".")),"") -> 8 | H3: ='[1]Hoja 1'!H3 -> 1 | I3: ='[1]Hoja 1'!I3 -> 2 | J3: ='[1]Hoja 1'!J3 -> 3 | K3: =B3&"|"&D3&"|"&J3 -> GRUPO frutas|Piña|3 | L3: =COUNTIFS($K$2:K3,K3)>1 -> FALSE | M3: =(G3="") -> FALSE | N3: =NOT(OR(L3,M3)) -> TRUE | O3: =IF(N3,G3,"") -> 8 | P3: =IF(N3,H3,"") -> 1 | Q3: =IF(N3,I3,"") -> 2
A4: ='[1]Hoja 1'!A4 -> 3 | B4: ='[1]Hoja 1'!B4 -> GRUPO frutas | C4: ='[1]Hoja 1'!C4 -> GRUPO SUPER | D4: ='[1]Hoja 1'!D4 -> Papaya | E4: ='[1]Hoja 1'!E4 -> Frutas grande | F4: =IFERROR(VALUE(SUBSTITUTE('[1]Hoja 1'!F4,".","")),"") -> 6 | G4: =IFERROR(VALUE(SUBSTITUTE(SUBSTITUTE('[1]Hoja 1'!G4,".",""),",",".")),"") -> 6 | H4: ='[1]Hoja 1'!H4 -> 3 | I4: ='[1]Hoja 1'!I4 -> 1 | J4: ='[1]Hoja 1'!J4 -> 1 | K4: =B4&"|"&D4&"|"&J4 -> GRUPO frutas|Papaya|1 | L4: =COUNTIFS($K$2:K4,K4)>1 -> FALSE | M4: =(G4="") -> FALSE | N4: =NOT(OR(L4,M4)) -> TRUE | O4: =IF(N4,G4,"") -> 6 | P4: =IF(N4,H4,"") -> 3 | Q4: =IF(N4,I4,"") -> 1
A5: ='[1]Hoja 1'!A5 -> 4 | B5: ='[1]Hoja 1'!B5 -> GRUPO frutas | C5: ='[1]Hoja 1'!C5 -> 0 | D5: ='[1]Hoja 1'!D5 -> Sandía | E5: ='[1]Hoja 1'!E5 -> Frutas grande | F5: =IFERROR(VALUE(SUBSTITUTE('[1]Hoja 1'!F5,".","")),"") -> 8 | G5: =IFERROR(VALUE(SUBSTITUTE(SUBSTITUTE('[1]Hoja 1'!G5,".",""),",",".")),"") -> 8 | H5: ='[1]Hoja 1'!H5 -> 0 | I5: ='[1]Hoja 1'!I5 -> 5 | J5: ='[1]Hoja 1'!J5 -> 0 | K5: =B5&"|"&D5&"|"&J5 -> GRUPO frutas|Sandía|0 | L5: =COUNTIFS($K$2:K5,K5)>1 -> FALSE | M5: =(G5="") -> FALSE | N5: =NOT(OR(L5,M5)) -> TRUE | O5: =IF(N5,G5,"") -> 8 | P5: =IF(N5,H5,"") -> 0 | Q5: =IF(N5,I5,"") -> 5
A6: ='[1]Hoja 1'!A6 -> 5 | B6: ='[1]Hoja 1'!B6 -> GRUPO frutas | C6: ='[1]Hoja 1'!C6 -> GRUPO MAQUILLAJE | D6: ='[1]Hoja 1'!D6 -> Manzana | E6: ='[1]Hoja 1'!E6 -> Frutas mediana | F6: =IFERROR(VALUE(SUBSTITUTE('[1]Hoja 1'!F6,".","")),"") -> 3.5 | G6: =IFERROR(VALUE(SUBSTITUTE('[1]Hoja 1'!G6,".","")),"") -> 3.5 | H6: ='[1]Hoja 1'!H6 -> 1 | I6: ='[1]Hoja 1'!I6 -> 4 | J6: ='[1]Hoja 1'!J6 -> 1 | K6: =B6&"|"&D6&"|"&J6 -> GRUPO frutas|Manzana|1 | L6: =COUNTIFS($K$2:K6,K6)>1 -> FALSE | M6: =(G6="") -> FALSE | N6: =NOT(OR(L6,M6)) -> TRUE | O6: =IF(N6,G6,"") -> 3.5 | P6: =IF(N6,H6,"") -> 1 | Q6: =IF(N6,I6,"") -> 4
A7: ='[1]Hoja 1'!A7 -> 6 | B7: ='[1]Hoja 1'!B7 -> GRUPO frutas | C7: ='[1]Hoja 1'!C7 -> GRUPO SUPER | D7: ='[1]Hoja 1'!D7 -> Banano | E7: ='[1]Hoja 1'!E7 -> Frutas mediana | F7: =IFERROR(VALUE(SUBSTITUTE('[1]Hoja 1'!F7,".","")),"") -> 4 | G7: =IFERROR(VALUE(SUBSTITUTE(SUBSTITUTE('[1]Hoja 1'!G7,".",""),",",".")),"") -> 4 | H7: ='[1]Hoja 1'!H7 -> 1 | I7: ='[1]Hoja 1'!I7 -> 3 | J7: ='[1]Hoja 1'!J7 -> 1 | K7: =B7&"|"&D7&"|"&J7 -> GRUPO frutas|Banano|1 | L7: =COUNTIFS($K$2:K7,K7)>1 -> FALSE | M7: =(G7="") -> FALSE | N7: =NOT(OR(L7,M7)) -> TRUE | O7: =IF(N7,G7,"") -> 4 | P7: =IF(N7,H7,"") -> 1 | Q7: =IF(N7,I7,"") -> 3
A8: ='[1]Hoja 1'!A8 -> 7 | B8: ='[1]Hoja 1'!B8 -> GRUPO frutas | C8: ='[1]Hoja 1'!C8 -> GRUPO POSTRES | D8: ='[1]Hoja 1'!D8 -> Uva | E8: ='[1]Hoja 1'!E8 -> Frutas pequeña | F8: =IFERROR(VALUE(SUBSTITUTE('[1]Hoja 1'!F8,".","")),"") -> 9 | G8: =IFERROR(VALUE(SUBSTITUTE(SUBSTITUTE('[1]Hoja 1'!G8,".",""),",",".")),"") -> 10 | H8: ='[1]Hoja 1'!H8 -> 1 | I8: ='[1]Hoja 1'!I8 -> 4 | J8: ='[1]Hoja 1'!J8 -> 3 | K8: =B8&"|"&D8&"|"&J8 -> GRUPO frutas|Uva|3 | L8: =COUNTIFS($K$2:K8,K8)>1 -> FALSE | M8: =(G8="") -> FALSE | N8: =NOT(OR(L8,M8)) -> TRUE | O8: =IF(N8,G8,"") -> 10 | P8: =IF(N8,H8,"") -> 1 | Q8: =IF(N8,I8,"") -> 4
A9: ='[1]Hoja 1'!A9 -> 8 | B9: ='[1]Hoja 1'!B9 -> GRUPO frutas | C9: ='[1]Hoja 1'!C9 -> 0 | D9: ='[1]Hoja 1'!D9 -> Naranja | E9: ='[1]Hoja 1'!E9 -> Frutas mediana | F9: =IFERROR(VALUE(SUBSTITUTE('[1]Hoja 1'!F9,".","")),"") -> 3 | G9: =IFERROR(VALUE(SUBSTITUTE(SUBSTITUTE('[1]Hoja 1'!G9,".",""),",",".")),"") -> 3 | H9: ='[1]Hoja 1'!H9 -> 0 | I9: ='[1]Hoja 1'!I9 -> 3 | J9: ='[1]Hoja 1'!J9 -> 0 | K9: =B9&"|"&D9&"|"&J9 -> GRUPO frutas|Naranja|0 | L9: =COUNTIFS($K$2:K9,K9)>1 -> FALSE | M9: =(G9="") -> FALSE | N9: =NOT(OR(L9,M9)) -> TRUE | O9: =IF(N9,G9,"") -> 3 | P9: =IF(N9,H9,"") -> 0 | Q9: =IF(N9,I9,"") -> 3
A10: ='[1]Hoja 1'!A10 -> 9 | B10: ='[1]Hoja 1'!B10 -> GRUPO frutas | C10: ='[1]Hoja 1'!C10 -> GRUPO POSTRES | D10: ='[1]Hoja 1'!D10 -> Lima | E10: ='[1]Hoja 1'!E10 -> Frutas pequeña | F10: =IFERROR(VALUE(SUBSTITUTE('[1]Hoja 1'!F10,".","")),"") -> 2 | G10: =IFERROR(VALUE(SUBSTITUTE(SUBSTITUTE('[1]Hoja 1'!G10,".",""),",",".")),"") -> 2 | H10: ='[1]Hoja 1'!H10 -> 2 | I10: ='[1]Hoja 1'!I10 -> 4 | J10: ='[1]Hoja 1'!J10 -> 2 | K10: =B10&"|"&D10&"|"&J10 -> GRUPO frutas|Lima|2 | L10: =COUNTIFS($K$2:K10,K10)>1 -> FALSE | M10: =(G10="") -> FALSE | N10: =NOT(OR(L10,M10)) -> TRUE | O10: =IF(N10,G10,"") -> 2 | P10: =IF(N10,H10,"") -> 2 | Q10: =IF(N10,I10,"") -> 4
A11: ='[1]Hoja 1'!A11 -> 10 | B11: ='[1]Hoja 1'!B11 -> GRUPO frutas | C11: ='[1]Hoja 1'!C11 -> GRUPO SUPER | D11: ='[1]Hoja 1'!D11 -> Pitahaya | E11: ='[1]Hoja 1'!E11 -> Frutas mediana | F11: =IFERROR(VALUE(SUBSTITUTE('[1]Hoja 1'!F11,".","")),"") -> 8 | G11: =IFERROR(VALUE(SUBSTITUTE(SUBSTITUTE('[1]Hoja 1'!G11,".",""),",",".")),"") -> 8 | H11: ='[1]Hoja 1'!H11 -> 1 | I11: ='[1]Hoja 1'!I11 -> 3 | J11: ='[1]Hoja 1'!J11 -> 1 | K11: =B11&"|"&D11&"|"&J11 -> GRUPO frutas|Pitahaya|1 | L11: =COUNTIFS($K$2:K11,K11)>1 -> FALSE | M11: =(G11="") -> FALSE | N11: =NOT(OR(L11,M11)) -> TRUE | O11: =IF(N11,G11,"") -> 8 | P11: =IF(N11,H11,"") -> 1 | Q11: =IF(N11,I11,"") -> 3
A12: ='[1]Hoja 1'!A12 -> 11 | B12: ='[1]Hoja 1'!B12 -> GRUPO frutas | C12: ='[1]Hoja 1'!C12 -> GRUPO MAQUILLAJE | D12: ='[1]Hoja 1'!D12 -> Cereza | E12: ='[1]Hoja 1'!E12 -> Frutas pequeña | F12: =IFERROR(VALUE(SUBSTITUTE('[1]Hoja 1'!F12,".","")),"") -> 6 | G12: =IFERROR(VALUE(SUBSTITUTE(SUBSTITUTE('[1]Hoja 1'!G12,".",""),",",".")),"") -> 6 | H12: ='[1]Hoja 1'!H12 -> 1 | I12: ='[1]Hoja 1'!I12 -> 3 | J12: ='[1]Hoja 1'!J12 -> 3 | K12: =B12&"|"&D12&"|"&J12 -> GRUPO frutas|Cereza|3 | L12: =COUNTIFS($K$2:K12,K12)>1 -> FALSE | M12: =(G12="") -> FALSE | N12: =NOT(OR(L12,M12)) -> TRUE | O12: =IF(N12,G12,"") -> 6 | P12: =IF(N12,H12,"") -> 1 | Q12: =IF(N12,I12,"") -> 3
A13: ='[1]Hoja 1'!A13 -> 12 | B13: ='[1]Hoja 1'!B13 -> GRUPO frutas | C13: ='[1]Hoja 1'!C13 -> GRUPO SUPER | D13: ='[1]Hoja 1'!D13 -> Arándanos | E13: ='[1]Hoja 1'!E13 -> Frutas pequeña | F13: =IFERROR(VALUE(SUBSTITUTE('[1]Hoja 1'!F13,".","")),"") -> 8 | G13: =IFERROR(VALUE(SUBSTITUTE(SUBSTITUTE('[1]Hoja 1'!G13,".",""),",",".")),"") -> 10 | H13: ='[1]Hoja 1'!H13 -> 1 | I13: ='[1]Hoja 1'!I13 -> 1 | J13: ='[1]Hoja 1'!J13 -> 3 | K13: =B13&"|"&D13&"|"&J13 -> GRUPO frutas|Arándanos|3 | L13: =COUNTIFS($K$2:K13,K13)>1 -> FALSE | M13: =(G13="") -> FALSE | N13: =NOT(OR(L13,M13)) -> TRUE | O13: =IF(N13,G13,"") -> 10 | P13: =IF(N13,H13,"") -> 1 | Q13: =IF(N13,I13,"") -> 1

Sheet Univariado
A1: Mínimo | B1: =MIN(Datos!G:G) -> 2.5
A2: Máximo | B2: =MAX(Datos!G:G) -> 74
A3: Desviación estándar | B3: =_xlfn.STDEV.S(Datos!G:G) -> 17.730534
A4: Q1 | B4: =_xlfn.QUARTILE.INC(Datos!G:G,1) -> 4.65
A5: Mediana | B5: =MEDIAN(Datos!G:G) -> 6
A6: Q3 | B6: =_xlfn.QUARTILE.INC(Datos!G:G,3) -> 9
A7: Límite inferior outlier (Q1-1.5·RIC) | B7: =B4-1.5*(B6-B4) -> -1.875
A8: Límite superior outlier (Q3+1.5·RIC) | B8: =B6+1.5*(B6-B4) -> 15.525
A10: Categoría | B10: Ventas (sin duplicados)
A11: Frutas pequeñas | B11: 4
A12: Frutas medianas | B12: 5
A13: Frutas grandes | B13: 3

Sheet Bivariado
A1: Precio promedio por categoría
A2: Categoría | B2: Precio promedio
A3: Frutas pequeñas | B3: =(Limpieza!G10+Limpieza!G12+Limpieza!G13+Limpieza!G8)/4 -> 7
A4: Frutas medianas | B4: =Limpieza!G2+Limpieza!G6+Limpieza!G9+Limpieza!G11/4 -> 11
A5: Frutas grandes | B5: =(Limpieza!G3+Limpieza!G4+Limpieza!G5)/3 -> 7.3333333
A8: Ingresos por vendedor
A9: Vendedor | B9: Ingreso total
A10: Grupo frutas | B10: =SUM(Limpieza!G2:G13) -> 71

Sheet Correlación
A1: Correlación calificación vs precio de venta
A3: Coeficiente de correlación | B3: =CORREL(Limpieza!$Q$2:$Q$13, Limpieza!$O$2:$O$13) -> -0.36162505
A4: Interpretación | B4: =IF(ABS(B3)>=0.7,"Correlación fuerte",IF(ABS(B3)>=0.3,"Correlación moderada","Correlación débil"))&IF(B3>=0," positiva."," negativa.") -> Correlación moderada negativa.
A6: Recuerda: correlación no implica causalidad.

Sheet Hoja1
A1: Conclusiones
A3: Hallazgo 1 | B3: Las frutas medianas tienen el precio promedio de venta más alto, con 11.
A5: Hallazgo 2 | B5: La calificación y el precio de venta tienen una correlación negativa moderada de -0,36.
A7: Hipótesis a validar | B7: A mayor precio de venta, menor podría ser la calificación del producto.
